linstall/__init__.py
linstall/console.py
linstall/templates/__init__.py
linstall/templates/javascript.md
linstall/templates/python.md
linstall-0.2.2.dist-info/entry_points.txt
linstall-0.2.2.dist-info/LICENSE
linstall-0.2.2.dist-info/WHEEL
linstall-0.2.2.dist-info/METADATA
linstall-0.2.2.dist-info/RECORD
