Metadata-Version: 2.1
Name: linstall
Version: 0.2.2
Summary: A Python CLI to generate a list of installation commands for a package to add to README files.
Home-page: https://github.com/joaopalmeiro/linstall
License: MIT
Author: João Palmeiro
Author-email: joaopalmeiro@proton.me
Requires-Python: >=3.7,<4.0
Classifier: License :: OSI Approved :: MIT License
Classifier: Programming Language :: Python :: 3
Classifier: Programming Language :: Python :: 3.7
Classifier: Programming Language :: Python :: 3.8
Classifier: Programming Language :: Python :: 3.9
Classifier: Programming Language :: Python :: 3.10
Requires-Dist: click (==8.1.3)
Requires-Dist: markdown-subtemplate (==0.2.22)
Requires-Dist: pyperclip (==1.8.2)
Project-URL: Bug Tracker, https://github.com/joaopalmeiro/linstall/issues
Project-URL: Repository, https://github.com/joaopalmeiro/linstall
Project-URL: Twitter, https://twitter.com/joaompalmeiro
